setup.py
orgo/__init__.py
orgo/models.py
orgo/orgo_client.py
orgo_pylib.egg-info/PKG-INFO
orgo_pylib.egg-info/SOURCES.txt
orgo_pylib.egg-info/dependency_links.txt
orgo_pylib.egg-info/requires.txt
orgo_pylib.egg-info/top_level.txt